{
    "艺术字花体字/艺术字花体字_0013.jpg": {
        "mt": "Imagen real del efecto  \nLos envases tradicionales suelen ser de hojalata, cartón, plástico, etc. Aunque este tipo de cajas también pueden proteger bien el producto, no pueden mostrar la apariencia y las características del producto de manera inmediata.  \nTampoco pueden satisfacer los requisitos de crear un empaque diferenciado y mejorar el efecto de marketing del producto. Por otro lado, las cajas transparentes no solo permiten a los consumidores ver y conocer el producto de inmediato, sino que también pueden aumentar su poder de compra.",
        "src": [
            "实物效果图",
            "传统的包装盒多为铁盒，纸盒，塑料等包装，虽然这类包装盒也能很好的保护产品，但他们都不能第一时间的展现产品的外观和特点，更不能满足打造差异化包装和提升产品营销效果的要求，而透明包装盒除了可以让消费者第一时间看到产品，了解产品，还能提升消费者购买力。"
        ]
    },
    "艺术字花体字/艺术字花体字_0025.jpg": {
        "mt": "Estilo: Zapatillas deportivas de moda  \nMaterial de la parte superior: Tejido cómodo  \nColores: Blanco, negro, rojo, gris  \nMaterial de la suela: Suela antideslizante  \nDiseño: Moderno y personalizado  \nMaterial del forro: Forro cómodo  \nSUP",
        "src": [
            "风格：运动潮鞋",
            "鞋面材质：舒适面料",
            "颜色：白色 黑色 红色 灰色",
            "鞋底材质：防滑大底",
            "设计：个性时尚",
            "内里材质：舒适内里",
            "清凉",
            "透气"
        ]
    },
    "艺术字花体字/艺术字花体字_0034.jpg": {
        "mt": "Dos deliciosos sabores  \nPara satisfacer el paladar  \nMás de 10 mil millones de paquetes vendidos  \nKonjac Shuang  \nPicante y masticable  \nKonjac Shuang  \nTres sabores  \n(Picante, Mala, Ácido y picante)  \nKonjac \"Tripa Vegetal\"  \nComienza  \nA comer picante  \nSabor a olla caliente  \nLa combinación perfecta  \nSabor picante y olla caliente con salsa de sésamo》",
        "src": [
            "两种美味",
            "满足味蕾",
            "魔芋爽",
            "香辣Q弹",
            "三种口味",
            "（香辣、麻辣、酸辣）",
            "魔芋素毛肚",
            "火锅味",
            "真绝配",
            "（香辣、麻酱火锅味）"
        ]
    },
    "艺术字花体字/艺术字花体字_0040.jpg": {
        "mt": "DARLIE  \n好来  \n新口味 + 经典 fórmula  \n¿Comprar sin pensarlo?  \nSet de menta de té frutal DARLIE  \nDARLIE  \nDARLIE  \n好来  \nDARLIE  \nDARLIE  \n好来  \n好来  \nDARLIE  \n好来  \n好来  \nDoble menta  \nDoble menta  \nTecnología de protección fresca y potente  \nDoble menta  \nTeabio  \nLucha duradera contra el mal aliento  \nTecnología de flujo de protección fresca y potente  \nTeabio  \nFrescura duradera y limpieza  \nExtracto de té de alta calidad  \nProtección fresca y duradera  \nExtracto de té de sabor natural  \nProtección fresca y duradera  \nPMDED  \nPasta de dientes 120 g  \nLimpieza 00  \n2h de frescura duradera  \nFórmula para dientes fuertes  \nVariedad de sabores  \nMoléculas anti-mal aliento, esencia de doble menta  \nExtracto de té con polifenoles para dientes fuertes  \nSabor a té frutal, frescura natural  \n#Ver detalles en la página",
        "src": [
            "DARLIE",
            "好来",
            "新口味+经典配方",
            "囤货闭眼入",
            "好来果茶薄荷套组",
            "12h长效#清新",
            "健齿配方",
            "多样口味",
            "抗口气^分子，双重薄荷精华",
            "初萃茶多酚健齿",
            "果茶味、清新自然调",
            "#^详见详情页"
        ]
    },
    "艺术字花体字/艺术字花体字_0043.jpg": {
        "mt": "RG\nAurora boreal\nAlmacén espacial\nGALAXY\nCATW\nTapa del bolígrafo\nPunta integrada\nAutosellado\nFuncionalidad\nMagnético\nEstuche portátil\nPluma básica para practicar caligrafía\nEspacio\nAlmacén\nEspacio\nAcoplamiento\nPunta negra y dorada\nIncluye una punta de repuesto de alta resistencia\nEstuche magnético/negro\nIncluye 2 cartuchos de tinta de secado rápido (azul)",
        "src": [
            "太空储备仓",
            "内置笔尖一个",
            "磁吸盒装/黑色",
            "内置2支速干墨囊（蓝色）"
        ]
    },
    "艺术字花体字/艺术字花体字_0058.jpg": {
        "mt": "Fácil de usar  \nSelección de plantas herbales  \nCitronela  \nArtemisia  \nGirasol  \nArtemisia Ding Ding  \nParches de aceites esenciales vegetales  \nMenta  \nEucalipto",
        "src": [
            "简单易用",
            "甄选草本植物",
            "香茅",
            "艾草",
            "薄荷",
            "桉叶"
        ]
    },
    "艺术字花体字/艺术字花体字_0067.jpg": {
        "mt": "Durazno y ciruela  \nFeria de Año Nuevo  \nPan  \nHorario del evento: 6 de enero de 2025 20:00 - 20 de enero de 2025 23:59  \nDurazno y ciruela  \nDurazno y ciruela  \nDescuento de 30 yuan por cada 200 yuan en compras cruzadas  \nLevadura  \nPan de levadura  \nPan de levadura  \nSuave, esponjoso y delicioso  \n+ Horas de trabajo cultural en la capital  \nRecarga de saldo en la página principal de la tienda  \nRecarga 100, obtén 8  \nObtén 18  \nRecarga 200  \nProceso de fermentación a baja temperatura durante 24 horas  \n50  \nObtén  \nRecarga 500  \nÚnete gratis y disfruta de los beneficios de membresía",
        "src": [
            "桃李面包",
            "年货节",
            "活动时间：2025年1月6日20：00-2025年1月20日23：59",
            "跨店每满",
            "200减30元",
            "柔软蓬松 松软可口",
            "店铺首页充购物金",
            "充100送8",
            "充200送18",
            "24小时低温发酵工艺",
            "充500送50",
            "0元入会尊享会员权益",
            "天猫"
        ]
    }
}