{
    "ch_13.jpg": {
        "mt": "Shared bicycles  \nProhibited from entering",
        "ref": [
            "Shared Bike",
            "No Entrance"
        ],
        "src": [
            "共享单车",
            "禁止入内"
        ]
    },
    "ch_167.jpg": {
        "mt": "The Way of Nature",
        "ref": [
            "The Way of Nature"
        ],
        "src": [
            "自然之道"
        ]
    },
    "ch_14.jpg": {
        "mt": "Ticket Office →",
        "ref": [
            "Manual Ticket Office"
        ],
        "src": [
            "人工售票处"
        ]
    },
    "ch_160.jpg": {
        "mt": "SF Express Shipping\n\nPremium Extra Large Fruit Packaging",
        "ref": [
            "SF Express",
            "Boutique oversized fruit"
        ],
        "src": [
            "S顺丰速运",
            "精品特大果装"
        ]
    },
    "ch_68.jpg": {
        "mt": "China Construction Plaza",
        "ref": [
            "Zhongjian Plaza"
        ],
        "src": [
            "中建广场"
        ]
    },
    "ch_66.jpg": {
        "mt": "Golden Splendor Hotel",
        "ref": [
            "Jin Can Hotel"
        ],
        "src": [
            "金灿酒店"
        ]
    },
    "ch_112.jpg": {
        "mt": "Aima",
        "ref": [
            "Aima"
        ],
        "src": [
            "爱玛"
        ]
    },
    "ch_61.jpg": {
        "mt": "Honor Mission Science Dream",
        "ref": [
            "Science Dream"
        ],
        "src": [
            "科学梦"
        ]
    },
    "ch_115.jpg": {
        "mt": "For Rent  \nVacant and Ready",
        "ref": [
            "For Rent",
            "Vacant Position"
        ],
        "src": [
            "招租",
            "虚位以待"
        ]
    },
    "ch_169.jpg": {
        "mt": "Mountain Bamboo Fruit",
        "ref": [
            "mangosteen"
        ],
        "src": [
            "山竹果"
        ]
    },
    "ch_54.jpg": {
        "mt": "Big Sister Dumplings",
        "ref": [
            "Da Niang Dumpling"
        ],
        "src": [
            "大娘水饺"
        ]
    },
    "ch_85.jpg": {
        "mt": "Beautiful Island Garden",
        "ref": [
            "Li Dao Garden"
        ],
        "src": [
            "丽岛花园"
        ]
    },
    "ch_120.jpg": {
        "mt": "Construction site  \nDo not pass through",
        "ref": [
            "CONSTRUCTION SITE, NO ADMITTANCE"
        ],
        "src": [
            "施工重地",
            "请勿穿行"
        ]
    },
    "ch_28.jpg": {
        "mt": "Rush to  \nMountains and Seas",
        "ref": [
            "Go to, hills and seas"
        ],
        "src": [
            "奔赴",
            "山海"
        ]
    },
    "ch_8.jpg": {
        "mt": "Fire extinguisher",
        "ref": [
            "Fire Extinguisher"
        ],
        "src": [
            "灭火器"
        ]
    },
    "ch_53.jpg": {
        "mt": "Jinghua Cloth Shoes®",
        "ref": [
            "Jinghua Cloth Shoes"
        ],
        "src": [
            "京花布鞋"
        ]
    },
    "ch_82.jpg": {
        "mt": "Welcome to the Yellow Crane Tower!",
        "ref": [
            "Yellow Crane Tower, Welcome!"
        ],
        "src": [
            "黄鹤楼",
            "欢迎您！"
        ]
    },
    "ch_127.jpg": {
        "mt": "Free Snack Area",
        "ref": [
            "Free Snack Zone"
        ],
        "src": [
            "免费小吃区"
        ]
    },
    "ch_21.jpg": {
        "mt": "30\n150m↑\nSchool Zone",
        "ref": [
            "30",
            "150m",
            "School Zone"
        ],
        "src": [
            "30",
            "150m个",
            "学校区域"
        ]
    },
    "ch_6.jpg": {
        "mt": "Please Stop Here for Staff Picking Up Passengers!\nPassenger Only!",
        "ref": [
            "Passenger Only!",
            "Passenger Only!"
        ],
        "src": [
            "接站人员请止步！",
            "Passenger Only!"
        ]
    },
    "ch_155.jpg": {
        "mt": "Yilin",
        "ref": [
            "Yi Forest"
        ],
        "src": [
            "逸林"
        ]
    },
    "ch_184.jpg": {
        "mt": "Before applying the film\n\nAfter applying the film",
        "ref": [
            "Before lamination",
            "After lamination"
        ],
        "src": [
            "贴膜前",
            "贴膜后"
        ]
    },
    "ch_129.jpg": {
        "mt": "High voltage danger, do not approach",
        "ref": [
            "DANGER HIGH VOLTAGE KEEP OUT"
        ],
        "src": [
            "高压危险禁止靠近"
        ]
    },
    "ch_26.jpg": {
        "mt": "Fire Elevator",
        "ref": [
            "fire elevator"
        ],
        "src": [
            "消防电梯"
        ]
    },
    "ch_1.jpg": {
        "mt": "Under Construction\n\nPlease Do Not Approach",
        "ref": [
            "Under Construction",
            "Keep away"
        ],
        "src": [
            "正在施工",
            "请勿靠近"
        ]
    },
    "ch_152.jpg": {
        "mt": "Little Gold Thread Alley HUTONG",
        "ref": [
            "XiaoJinsi Hutong",
            "XIAOJINSI HUTONG"
        ],
        "src": [
            "小金丝胡同",
            "XIAOJINSI HUTONG"
        ]
    },
    "ch_183.jpg": {
        "mt": "Thicker! More durable",
        "ref": [
            "Thicken! More durable"
        ],
        "src": [
            "加厚！更耐用"
        ]
    },
    "ch_143.jpg": {
        "mt": "Park North Gate Exit →",
        "ref": [
            "North Exit of Park"
        ],
        "src": [
            "公园北门出口"
        ]
    },
    "ch_37.jpg": {
        "mt": "Jian Yin Hotel",
        "ref": [
            "Jianyin Restaurant"
        ],
        "src": [
            "建银饭店"
        ]
    },
    "ch_144.jpg": {
        "mt": "Sales of aviation insurance\n\nEach copy 20 yuan\n\nInsurance period 7 days",
        "ref": [
            "Aviation Insurance on Sale",
            "20 RMB per piece",
            "Insurance Period: 7 days"
        ],
        "src": [
            "销售航空保险",
            "每份20元",
            "保险期限7天"
        ]
    },
    "ch_30.jpg": {
        "mt": "Get off and push",
        "ref": [
            "Walk Your Bicycle"
        ],
        "src": [
            "下车推行"
        ]
    },
    "ch_138.jpg": {
        "mt": "Preferred Finance",
        "ref": [
            "Youxuan Finance"
        ],
        "src": [
            "优选金融"
        ]
    },
    "ch_136.jpg": {
        "mt": "February 20",
        "ref": [
            "February 20th"
        ],
        "src": [
            "2月20"
        ]
    },
    "ch_93.jpg": {
        "mt": "China Railway Heavy Industry",
        "ref": [
            "China Railway Heavy Industry"
        ],
        "src": [
            "中铁重工"
        ]
    },
    "ch_42.jpg": {
        "mt": "Standardize bicycle parking  \nJointly build a new civilized Haidian",
        "ref": [
            "Park bicycles regularly",
            "build new civilized Haidian"
        ],
        "src": [
            "规范停放自行车",
            "共建文明新海淀"
        ]
    },
    "ch_131.jpg": {
        "mt": "Sandfall and Cleaning",
        "ref": [
            "Shakeout and Clear"
        ],
        "src": [
            "落砂和清理"
        ]
    },
    "ch_94.jpg": {
        "mt": "South Finance Canteen",
        "ref": [
            "Nan Cai Grocery"
        ],
        "src": [
            "南财副食"
        ]
    },
    "ch_45.jpg": {
        "mt": "Tobacco  \nYu Ping Tobacco and Liquor Store",
        "ref": [
            "Yuping cigarette & wine store"
        ],
        "src": [
            "玉萍烟酒行"
        ]
    },
    "ch_39.jpg": {
        "mt": "Hangzhou City\nDetention Center\n1000m →",
        "ref": [
            "Hangzhou, detention house",
            "1000m"
        ],
        "src": [
            "杭州市",
            "拘留所",
            "1000m"
        ]
    },
    "ch_104.jpg": {
        "mt": "Please push to the right",
        "ref": [
            "Push Right Please"
        ],
        "src": [
            "请往右推"
        ]
    },
    "ch_70.jpg": {
        "mt": "Convenient Hardware Store\nConvenient Grain Oil and副Food",
        "ref": [
            "Convenient Hardware Store",
            "Convenient Grain Oil Grocery"
        ],
        "src": [
            "方便五金",
            "方便粮油副食"
        ]
    },
    "ch_178.jpg": {
        "mt": "Handmade Pure Steel Pot  \nBuy Now",
        "ref": [
            "Manual pure steel pot",
            "Buy now"
        ],
        "src": [
            "手工纯鋼锅",
            "立即加購"
        ]
    },
    "ch_103.jpg": {
        "mt": "Police Duty Point",
        "ref": [
            "Police Duty Point"
        ],
        "src": [
            "警城执勤点"
        ]
    },
    "ch_77.jpg": {
        "mt": "Li Ji Crispy Fried Dough Sticks",
        "ref": [
            "Li Crispy Fried Dough Sticks"
        ],
        "src": [
            "李记酥油条"
        ]
    },
    "ch_171.jpg": {
        "mt": "Hot Pot and Barbecue",
        "ref": [
            "Hot pot&Barbecue"
        ],
        "src": [
            "火锅烧烤"
        ]
    },
    "ch_79.jpg": {
        "mt": "Gear oil",
        "ref": [
            "Gear Oil"
        ],
        "src": [
            "齿轮机油"
        ]
    },
    "ch_176.jpg": {
        "mt": "More Precious Sleeves",
        "ref": [
            "More mini"
        ],
        "src": [
            "更袖珍"
        ]
    },
    "ch_27.jpg": {
        "mt": "Grateful for you",
        "ref": [
            "be grateful, to have you"
        ],
        "src": [
            "感恩",
            "有你"
        ]
    },
    "ch_153.jpg": {
        "mt": "Beijing Hyundai",
        "ref": [
            "Beijing Hyundai"
        ],
        "src": [
            "北京现代"
        ]
    },
    "ch_182.jpg": {
        "mt": "Small black pills, big effects\n\nPlum pills",
        "ref": [
            "Small black ball",
            "huge effect"
        ],
        "src": [
            "小黑丸",
            "大作用"
        ]
    },
    "ch_20.jpg": {
        "mt": "Improve the ecological environment  \nCreate a green home",
        "ref": [
            "improve the eco-environment",
            "Create a green home"
        ],
        "src": [
            "改善生态环境",
            "营造绿色家园"
        ]
    },
    "ch_7.jpg": {
        "mt": "So light  \nStill so strong  \nvivo",
        "ref": [
            "vivo",
            "So light, But so Strong"
        ],
        "src": [
            "vivo",
            "这么轻",
            "还那么强"
        ]
    },
    "ch_154.jpg": {
        "mt": "Ji Xing Ancestor Master  \nRelic Exhibition",
        "ref": [
            "JiXing Master",
            "Sarira Exhibition"
        ],
        "src": [
            "际醒祖师",
            "舍利展"
        ]
    },
    "ch_185.jpg": {
        "mt": "Pretty good",
        "ref": [
            "Good Job"
        ],
        "src": [
            "整挺好"
        ]
    },
    "ch_128.jpg": {
        "mt": "Holy Elephant Flooring",
        "ref": [
            "PowerDekor"
        ],
        "src": [
            "圣象地板"
        ]
    },
    "ch_9.jpg": {
        "mt": "Take the subway  \nTravel Nanjing",
        "ref": [
            "Travel Nanjing, By metro"
        ],
        "src": [
            "搭地铁",
            "游南京"
        ]
    },
    "ch_52.jpg": {
        "mt": "Fire Hydrant\nFIREHYDRANT\n2-5",
        "ref": [
            "Fire Hydrant",
            "FIREHYDRANT",
            "2-5"
        ],
        "src": [
            "消火栓",
            "FIREHYDRANT",
            "2-5"
        ]
    },
    "ch_83.jpg": {
        "mt": "Magic Castle",
        "ref": [
            "Magic Castle"
        ],
        "src": [
            "魔法城堡"
        ]
    },
    "ch_126.jpg": {
        "mt": "Antifreeze",
        "ref": [
            "Antifreeze"
        ],
        "src": [
            "防冻液"
        ]
    },
    "ch_55.jpg": {
        "mt": "Fishing Service Counter",
        "ref": [
            "Fishing Service Office"
        ],
        "src": [
            "垂钓服务台"
        ]
    },
    "ch_84.jpg": {
        "mt": "Rest and Reading  \nFree Charging",
        "ref": [
            "Rest or Read",
            "Free Charge"
        ],
        "src": [
            "休息阅读",
            "免费充电"
        ]
    },
    "ch_121.jpg": {
        "mt": "Xuande Furnace",
        "ref": [
            "Xuande Furnace"
        ],
        "src": [
            "宣德炉"
        ]
    },
    "ch_29.jpg": {
        "mt": "Gratitude  \nRelatives and Friends",
        "ref": [
            "be grateful to, relatives and friends"
        ],
        "src": [
            "感恩",
            "亲友"
        ]
    },
    "ch_60.jpg": {
        "mt": "Special Police\n\nCHINA NORTH INDUSTRIES GROUP CORPORATION",
        "ref": [
            "SWAT"
        ],
        "src": [
            "特警"
        ]
    },
    "ch_114.jpg": {
        "mt": "Danger at Heights  \nIn case of accidents",
        "ref": [
            "Height Danger",
            "Aware Accident"
        ],
        "src": [
            "高处危险",
            "如有意外"
        ]
    },
    "ch_168.jpg": {
        "mt": "Force a smile",
        "ref": [
            "Forced Laughter"
        ],
        "src": [
            "强颜欢笑"
        ]
    },
    "ch_67.jpg": {
        "mt": "Teddy Bridal Makeup",
        "ref": [
            "Teddy Dress Shop"
        ],
        "src": [
            "泰迪裙妆"
        ]
    },
    "ch_113.jpg": {
        "mt": "Pouring",
        "ref": [
            "Pouring"
        ],
        "src": [
            "浇注"
        ]
    },
    "ch_15.jpg": {
        "mt": "",
        "ref": [
            "Exit"
        ],
        "src": [
            "出口"
        ]
    },
    "ch_161.jpg": {
        "mt": "Regular medication",
        "ref": [
            "Take medicine regularly"
        ],
        "src": [
            "规律服药"
        ]
    },
    "ch_69.jpg": {
        "mt": "Golden纺 Towels\nFresh",
        "ref": [
            "Fresh",
            "JinFang Towel Shop"
        ],
        "src": [
            "鲜",
            "金纺毛巾"
        ]
    },
    "ch_12.jpg": {
        "mt": "Life is hot, how can it not be wild",
        "ref": [
            "Life is wonderful; why not play around"
        ],
        "src": [
            "人生滚烫岂能不浪"
        ]
    },
    "ch_166.jpg": {
        "mt": "Add oil",
        "ref": [
            "Add oil"
        ],
        "src": [
            "加油"
        ]
    },
    "ch_177.jpg": {
        "mt": "LED Light Box  \nWaterproof Sunscreen",
        "ref": [
            "LED Lightbox",
            "Waterproof and sun-protecting"
        ],
        "src": [
            "LED灯箱",
            "防水防晒"
        ]
    },
    "ch_170.jpg": {
        "mt": "You actually made me leave",
        "ref": [
            "you should kick me out"
        ],
        "src": [
            "你竟然赶我走"
        ]
    },
    "ch_78.jpg": {
        "mt": "Specialist Operation  \nPlease Do Not Touch",
        "ref": [
            "Special Operation",
            "No Touching"
        ],
        "src": [
            "专人操作",
            "请勿动手"
        ]
    },
    "ch_102.jpg": {
        "mt": "Purchase Ticket\nCollect Ticket",
        "ref": [
            "Buy Tickets",
            "Collect Tickets"
        ],
        "src": [
            "购票",
            "取票"
        ]
    },
    "ch_76.jpg": {
        "mt": "Bao Min Food and Miscellaneous",
        "ref": [
            "Bao Ming Food Store"
        ],
        "src": [
            "宝民食杂"
        ]
    },
    "ch_105.jpg": {
        "mt": "North",
        "ref": [
            "North"
        ],
        "src": [
            "北"
        ]
    },
    "ch_71.jpg": {
        "mt": "Creation Cloud Stone",
        "ref": [
            "Zaohua Marble"
        ],
        "src": [
            "造化云石"
        ]
    },
    "ch_179.jpg": {
        "mt": "5 points  \nYou are awesome",
        "ref": [
            "Good!"
        ],
        "src": [
            "你真棒"
        ]
    },
    "ch_130.jpg": {
        "mt": "Guangdong · Foshan",
        "ref": [
            "Guuangdong ・ Foshan"
        ],
        "src": [
            "广东·佛山"
        ]
    },
    "ch_95.jpg": {
        "mt": "Tasty Flavor Workshop",
        "ref": [
            "Gourmet Workshop"
        ],
        "src": [
            "美味坊"
        ]
    },
    "ch_44.jpg": {
        "mt": "Fire Prevention",
        "ref": [
            "fire prevention"
        ],
        "src": [
            "防火"
        ]
    },
    "ch_38.jpg": {
        "mt": "Ancient Fig Tree\n\nHetian County People's Government",
        "ref": [
            "Acient fig tree",
            "Hetian County People's Government"
        ],
        "src": [
            "古无花果树",
            "和田县人民政府"
        ]
    },
    "ch_137.jpg": {
        "mt": "Engine Oil",
        "ref": [
            "ENGINE OIL"
        ],
        "src": [
            "发动机油"
        ]
    },
    "ch_92.jpg": {
        "mt": "Foot Bath",
        "ref": [
            "Foot Bath"
        ],
        "src": [
            "足浴"
        ]
    },
    "ch_43.jpg": {
        "mt": "Dock area  \nFlood prevention passage  \nNo entry for unauthorized personnel",
        "ref": [
            "WHARF SITE",
            "FLOOD CONTROL CHANNEL",
            "NO ADMITTANCE"
        ],
        "src": [
            "码头重地",
            "防洪通道",
            "闲人免进"
        ]
    },
    "ch_145.jpg": {
        "mt": "Ticket Office\nTickets",
        "ref": [
            "Tickets",
            "Tickets"
        ],
        "src": [
            "售票处",
            "Tickets"
        ]
    },
    "ch_31.jpg": {
        "mt": "Warning\n\nDo not push the door Do not grab the door",
        "ref": [
            "Warn",
            "fall",
            "No scrabbling",
            "No pushing"
        ],
        "src": [
            "警告",
            "落",
            "请勿扒门",
            "请勿推门"
        ]
    },
    "ch_139.jpg": {
        "mt": "Scenic Area Up-Mountain Tourist Path",
        "ref": [
            "Scenic Mountain Tourism Line"
        ],
        "src": [
            "景区上山游道"
        ]
    },
    "ch_142.jpg": {
        "mt": "No Smoking",
        "ref": [
            "No smoking"
        ],
        "src": [
            "禁止吸烟"
        ]
    },
    "ch_36.jpg": {
        "mt": "Love sports, China has Anta",
        "ref": [
            "Love Sports China has ANTA"
        ],
        "src": [
            "爱运动 中国有安踏"
        ]
    },
    "ch_173.jpg": {
        "mt": "I'm having a really hard time.",
        "ref": [
            "Life is so hard"
        ],
        "src": [
            "我太难"
        ]
    },
    "ch_108.jpg": {
        "mt": "Elegant Cleanliness",
        "ref": [
            "Ya Jing Jie"
        ],
        "src": [
            "雅净洁"
        ]
    },
    "ch_174.jpg": {
        "mt": "Tea for leaders to drink",
        "ref": [
            "Tea for leaders"
        ],
        "src": [
            "领导喝的茶"
        ]
    },
    "ch_106.jpg": {
        "mt": "ING\nShare sweetness\nPass on happiness",
        "ref": [
            "ING",
            "Share Sweetness, Pass Happiness"
        ],
        "src": [
            "ING",
            "分享甜蜜",
            "传递快乐"
        ]
    },
    "ch_72.jpg": {
        "mt": "United Table Ball City",
        "ref": [
            "Lianhe Board Game City"
        ],
        "src": [
            "联和桌球城"
        ]
    },
    "ch_101.jpg": {
        "mt": "No Parking",
        "ref": [
            "No Parking"
        ],
        "src": [
            "禁止停车"
        ]
    },
    "ch_75.jpg": {
        "mt": "Sincere Prosperity Supermarket",
        "ref": [
            "Cheng Sheng Shop"
        ],
        "src": [
            "诚盛超市"
        ]
    },
    "ch_148.jpg": {
        "mt": "Niangziguan Station",
        "ref": [
            "Niangziguan Station"
        ],
        "src": [
            "娘子关站"
        ]
    },
    "ch_134.jpg": {
        "mt": "Advance Deposit  \nDirectly Doubled",
        "ref": [
            "Deposit in advance",
            "Double directly"
        ],
        "src": [
            "预存定金",
            "直接翻倍"
        ]
    },
    "ch_91.jpg": {
        "mt": "Pedestrian Walkway",
        "ref": [
            "Pedestrian Ways"
        ],
        "src": [
            "人行通道"
        ]
    },
    "ch_40.jpg": {
        "mt": "Road construction  \nRight lane closed",
        "ref": [
            "Road Construction",
            "Right Lane Ends"
        ],
        "src": [
            "道路施工",
            "右道封闭"
        ]
    },
    "ch_133.jpg": {
        "mt": "Multimedia Hall",
        "ref": [
            "Multi-media hall"
        ],
        "src": [
            "多媒体厅"
        ]
    },
    "ch_96.jpg": {
        "mt": "Special Chinese Cuisine  \nMass Consumption",
        "ref": [
            "Special Chinese food",
            "Ordinary consumption"
        ],
        "src": [
            "特色中餐",
            "大众消费"
        ]
    },
    "ch_47.jpg": {
        "mt": "Cliff! Do not approach",
        "ref": [
            "Cliff! Keep off"
        ],
        "src": [
            "悬崖禁止靠近"
        ]
    },
    "ch_98.jpg": {
        "mt": "Finished products warehousing",
        "ref": [
            "Product Storage"
        ],
        "src": [
            "成品入库"
        ]
    },
    "ch_49.jpg": {
        "mt": "Pizza Hut  \nHappy Restaurant  \nPizza and More™",
        "ref": [
            "Pizza Hut",
            "Happy restaurant",
            "Pizza and More"
        ],
        "src": [
            "必胜客",
            "欢乐餐厅",
            "Piuzand More"
        ]
    },
    "ch_190.jpg": {
        "mt": "Please Do Not Stop\nKeep Walking",
        "ref": [
            "Keep walking",
            "Keep Walking"
        ],
        "src": [
            "请勿停留",
            "Keep Walking"
        ]
    },
    "ch_141.jpg": {
        "mt": "Ideal Peking University, beautiful dream comes true",
        "ref": [
            "Peking University Dream comes true"
        ],
        "src": [
            "理想北大美梦成真"
        ]
    },
    "ch_35.jpg": {
        "mt": "Self-Selection Line B",
        "ref": [
            "self-service line B"
        ],
        "src": [
            "自选餐线B"
        ]
    },
    "ch_146.jpg": {
        "mt": "Enter the valley from here",
        "ref": [
            "Here into the Valley"
        ],
        "src": [
            "由此入谷"
        ]
    },
    "ch_32.jpg": {
        "mt": "Weak Electrical Shaft",
        "ref": [
            "weak electrical well"
        ],
        "src": [
            "弱电井"
        ]
    },
    "ch_23.jpg": {
        "mt": "From childhood, establish honesty and virtue",
        "ref": [
            "Establish the virtue of honesty from an early age"
        ],
        "src": [
            "从小树立诚信美德"
        ]
    },
    "ch_4.jpg": {
        "mt": "Fire Hydrant\n\nFIRE HYDRANT\n\nFire Alarm 69820119",
        "ref": [
            "Fire Hydrant",
            "FIRE HYDRANT",
            "Fire call:69820119"
        ],
        "src": [
            "消火栓",
            "FIRE HYDRANT",
            "火警69820119"
        ]
    },
    "ch_157.jpg": {
        "mt": "Attention",
        "ref": [
            "Notice"
        ],
        "src": [
            "注意"
        ]
    },
    "ch_186.jpg": {
        "mt": "Pay Attention to Safety",
        "ref": [
            "CAUTION"
        ],
        "src": [
            "注意安全"
        ]
    },
    "ch_58.jpg": {
        "mt": "Pengfei Hotel",
        "ref": [
            "Pengfei Hotel",
            "Hostel"
        ],
        "src": [
            "鹏飞宾馆",
            "旅"
        ]
    },
    "ch_89.jpg": {
        "mt": "Crocodile Fish",
        "ref": [
            "Crocodile"
        ],
        "src": [
            "鳄鱼"
        ]
    },
    "ch_24.jpg": {
        "mt": "Save energy and cherish resources",
        "ref": [
            "Save energy and cherish resources"
        ],
        "src": [
            "节能珍惜资源"
        ]
    },
    "ch_3.jpg": {
        "mt": "Closed",
        "ref": [
            "Closed",
            "Closed"
        ],
        "src": [
            "关闭",
            "Closed"
        ]
    },
    "ch_150.jpg": {
        "mt": "Strictly No Smoking  \nNo Smoking",
        "ref": [
            "No Smoking",
            "No, Smoking"
        ],
        "src": [
            "严禁吸烟",
            "No",
            "Smoking"
        ]
    },
    "ch_181.jpg": {
        "mt": "Halloween",
        "ref": [
            "Halloween"
        ],
        "src": [
            "万圣节"
        ]
    },
    "ch_56.jpg": {
        "mt": "Old Steamer",
        "ref": [
            "Bamboo Steamer"
        ],
        "src": [
            "老蒸笼"
        ]
    },
    "ch_87.jpg": {
        "mt": "Li Ning Specialty Store",
        "ref": [
            "Li Ning Specialty Store"
        ],
        "src": [
            "李宁专卖店"
        ]
    },
    "ch_122.jpg": {
        "mt": "Aoxing  \nDouble Low Rapeseed Oil",
        "ref": [
            "Ao Xing",
            "Double-low Rapeseed Oil"
        ],
        "src": [
            "奥星",
            "双低菜籽油"
        ]
    },
    "ch_159.jpg": {
        "mt": "Run, let's go",
        "ref": [
            "Keep running"
        ],
        "src": [
            "奔跑吧"
        ]
    },
    "ch_188.jpg": {
        "mt": "Take the subway  \nJust use \"Travel with Ning\"",
        "ref": [
            "take metro, use Go With Ning"
        ],
        "src": [
            "坐地铁",
            "就用“与宁同行"
        ]
    },
    "ch_51.jpg": {
        "mt": "Bright City汇",
        "ref": [
            "Mingcheng Store"
        ],
        "src": [
            "明城汇"
        ]
    },
    "ch_80.jpg": {
        "mt": "Restroom\nWC",
        "ref": [
            "Toilet",
            "WC"
        ],
        "src": [
            "卫生间",
            "WC"
        ]
    },
    "ch_125.jpg": {
        "mt": "Royal Crown",
        "ref": [
            "CROWN"
        ],
        "src": [
            "皇冠"
        ]
    },
    "ch_18.jpg": {
        "mt": "Previous station",
        "ref": [
            "Previous Station",
            "Previous"
        ],
        "src": [
            "上一站",
            "Previous"
        ]
    },
    "ch_64.jpg": {
        "mt": "Shi Da's tomorrow will be better",
        "ref": [
            "Shida; Tomorrow will be better"
        ],
        "src": [
            "石大明天更美好"
        ]
    },
    "ch_110.jpg": {
        "mt": "Wuling Rongguang\nShanghai GM Wuling",
        "ref": [
            "Wuling Rongguang"
        ],
        "src": [
            "五菱荣光"
        ]
    },
    "ch_63.jpg": {
        "mt": "Seven hundred and seventy-seven years",
        "ref": [
            "770;000 years"
        ],
        "src": [
            "七十七万年"
        ]
    },
    "ch_117.jpg": {
        "mt": "Recruitment for Private Tutoring",
        "ref": [
            "Recruit Tutor"
        ],
        "src": [
            "招聘家教"
        ]
    },
    "ch_119.jpg": {
        "mt": "Friendliness  \nTreat others as you would like to be treated",
        "ref": [
            "Kindness",
            "Put Yourself in Another’s Place"
        ],
        "src": [
            "友善",
            "推已及人"
        ]
    },
    "ch_11.jpg": {
        "mt": "Deep in the bustling city  \nAmong the human烟火",
        "ref": [
            "Deep city",
            "Prosperous world"
        ],
        "src": [
            "市井深处",
            "烟火人间"
        ]
    },
    "ch_165.jpg": {
        "mt": "Adult College Entrance Examination",
        "ref": [
            "adult, university entrance examination"
        ],
        "src": [
            "成人",
            "高考"
        ]
    },
    "ch_16.jpg": {
        "mt": "Orderly Parking  \nReverse into Garage",
        "ref": [
            "Orderly parking",
            "Reverse stall parking"
        ],
        "src": [
            "有序停放",
            "倒车入库"
        ]
    },
    "ch_162.jpg": {
        "mt": "Carp Streamer",
        "ref": [
            "Koinobori"
        ],
        "src": [
            "鲤鱼旗"
        ]
    },
    "ch_147.jpg": {
        "mt": "Clearwater Bay Grand Hotel\nHIGER",
        "ref": [
            "HIGER",
            "Qingshui Bay Hotel"
        ],
        "src": [
            "HIGER",
            "清水湾大酒店"
        ]
    },
    "ch_33.jpg": {
        "mt": "Strong Power Shaft",
        "ref": [
            "strong electric well"
        ],
        "src": [
            "强电井"
        ]
    },
    "ch_99.jpg": {
        "mt": "HL Premium Goods",
        "ref": [
            "HL Boutique"
        ],
        "src": [
            "HL精品"
        ]
    },
    "ch_48.jpg": {
        "mt": "Strictly prohibit fire and smoke",
        "ref": [
            "No Open Flames"
        ],
        "src": [
            "严禁烟火"
        ]
    },
    "ch_191.jpg": {
        "mt": "B147  \n24 hours free open  \nFree open 24 hours",
        "ref": [
            "B147",
            "24 Hours, Free open",
            "Free open 24 hours"
        ],
        "src": [
            "B147",
            "24小时",
            "免费开放",
            "Free open 24 hours"
        ]
    },
    "ch_140.jpg": {
        "mt": "Do not forget national humiliation, remember history",
        "ref": [
            "Never forget national humiliation; Remember the history."
        ],
        "src": [
            "不忘国耻牢记历史"
        ]
    },
    "ch_34.jpg": {
        "mt": "Water pipe shaft",
        "ref": [
            "Aqueduct well"
        ],
        "src": [
            "水管井"
        ]
    },
    "ch_132.jpg": {
        "mt": "Be careful of hitting your head",
        "ref": [
            "13207030888",
            "Mind your head"
        ],
        "src": [
            "13207030888",
            "小心碰头"
        ]
    },
    "ch_97.jpg": {
        "mt": "Ancient Town Real Scenery",
        "ref": [
            "Ancient Town‘s Scenery"
        ],
        "src": [
            "古镇实景"
        ]
    },
    "ch_46.jpg": {
        "mt": "No Smoking\nGuanyin Temple\n←",
        "ref": [
            "No Smoking",
            "Kanonji"
        ],
        "src": [
            "禁止吸烟",
            "观音寺"
        ]
    },
    "ch_149.jpg": {
        "mt": "Find a\n❤️❤️\nboyfriend",
        "ref": [
            "Find, a boyfriend"
        ],
        "src": [
            "找到",
            "男朋友"
        ]
    },
    "ch_135.jpg": {
        "mt": "Taste and Appreciate for Ten Years",
        "ref": [
            "Taste Ten-year-old wine"
        ],
        "src": [
            "品鉴十年"
        ]
    },
    "ch_90.jpg": {
        "mt": "Entire journey at high speed 230 kilometers",
        "ref": [
            "Full high-speed, at 230 km/h"
        ],
        "src": [
            "速230公里",
            "全程高速"
        ]
    },
    "ch_41.jpg": {
        "mt": "Kangjia Appliances",
        "ref": [
            "Konka Electric"
        ],
        "src": [
            "康佳电器"
        ]
    },
    "ch_100.jpg": {
        "mt": "No signal",
        "ref": [
            "No Signal"
        ],
        "src": [
            "无信号"
        ]
    },
    "ch_74.jpg": {
        "mt": "Xuan Yu Auto Repair",
        "ref": [
            "Xuan Yu Auto Repair"
        ],
        "src": [
            "轩宇汽车维修"
        ]
    },
    "ch_107.jpg": {
        "mt": "The campus is my home",
        "ref": [
            "School is home"
        ],
        "src": [
            "校园是我家"
        ]
    },
    "ch_73.jpg": {
        "mt": "Jin Jin General Store",
        "ref": [
            "Zhenzhen Grocery"
        ],
        "src": [
            "珍珍杂货店"
        ]
    },
    "ch_109.jpg": {
        "mt": "Streetlight",
        "ref": [
            "street lights"
        ],
        "src": [
            "路灯"
        ]
    },
    "ch_175.jpg": {
        "mt": "Lucky  \nBig Draw",
        "ref": [
            "Lucky, Lottery"
        ],
        "src": [
            "幸运",
            "大抽奖"
        ]
    },
    "ch_172.jpg": {
        "mt": "Prevent drowning  \nPrevent infectious diseases  \nRainy Day",
        "ref": [
            "Avoid Drowning",
            "Prevent infectious diseases"
        ],
        "src": [
            "防溺水",
            "防传染病"
        ]
    },
    "ch_17.jpg": {
        "mt": "Eliminate waste  \nPromote civilized dining  \nPlease cherish food",
        "ref": [
            "eliminate waste",
            "Advocate civilized dinning, Cherish the food"
        ],
        "src": [
            "杜绝浪费",
            "倡导文明就餐",
            "请珍惜粮食"
        ]
    },
    "ch_163.jpg": {
        "mt": "Patent Application\n\nBreakthrough Limitations\nPatent Application    Technical Protection",
        "ref": [
            "Patent Application",
            "Push the limits",
            "Patent Application",
            "Protect technology"
        ],
        "src": [
            "专利申请",
            "突破限制",
            "专利申请",
            "技术保护"
        ]
    },
    "ch_118.jpg": {
        "mt": "Han Kou",
        "ref": [
            "Hankou"
        ],
        "src": [
            "汉口"
        ]
    },
    "ch_10.jpg": {
        "mt": "Leave the kitchen\nRemember to turn off the stove",
        "ref": [
            "When leaving kitchen, Turn off the fire"
        ],
        "src": [
            "离开厨房",
            "记得关火"
        ]
    },
    "ch_164.jpg": {
        "mt": "Zhongming Construction",
        "ref": [
            "Zhongming Construction Company"
        ],
        "src": [
            "中明建设"
        ]
    },
    "ch_62.jpg": {
        "mt": "Avoidance",
        "ref": [
            "Avoid"
        ],
        "src": [
            "回避"
        ]
    },
    "ch_116.jpg": {
        "mt": "Teachers' Rest Room",
        "ref": [
            "Teacher's Lounge"
        ],
        "src": [
            "教师休息室"
        ]
    },
    "ch_19.jpg": {
        "mt": "Moving Freight\n15258831222",
        "ref": [
            "Move house&Freight",
            "15258831222"
        ],
        "src": [
            "搬家货运",
            "15258831222"
        ]
    },
    "ch_65.jpg": {
        "mt": "Baidu Autonomous Vehicle",
        "ref": [
            "Baidu pilotless automobile"
        ],
        "src": [
            "百度无人车"
        ]
    },
    "ch_111.jpg": {
        "mt": "Nuclear load 9 people",
        "ref": [
            "Gross Weight：9 persons"
        ],
        "src": [
            "核载9人"
        ]
    },
    "ch_158.jpg": {
        "mt": "230 pounds can be worn",
        "ref": [
            "people weigh 230 pounds can still wear"
        ],
        "src": [
            "230斤可以穿"
        ]
    },
    "ch_189.jpg": {
        "mt": "Come scan the code to download and use it\n\nOfficial Announcement Electronic Invoice",
        "ref": [
            "Scan the code to download and use",
            "electronic invoice",
            "official pronouncements"
        ],
        "src": [
            "扫码下载使用吧",
            "电子发票",
            "官方公告"
        ]
    },
    "ch_50.jpg": {
        "mt": "KFC",
        "ref": [
            "KFC"
        ],
        "src": [
            "肯德基"
        ]
    },
    "ch_81.jpg": {
        "mt": "Wallpaper Wallcloth",
        "ref": [
            "Wallpaper&Wall covering"
        ],
        "src": [
            "墙纸墙布"
        ]
    },
    "ch_124.jpg": {
        "mt": "Leisure Beverages",
        "ref": [
            "Leisure Drink"
        ],
        "src": [
            "休闲饮料"
        ]
    },
    "ch_57.jpg": {
        "mt": "aigo Lover",
        "ref": [
            "aigo",
            "aigo"
        ],
        "src": [
            "aigo",
            "爱国者"
        ]
    },
    "ch_86.jpg": {
        "mt": "Be careful of the steps\nBe careful of the steps",
        "ref": [
            "Mind the Step",
            "Mind the Step"
        ],
        "src": [
            "小心台阶",
            "小心台阶"
        ]
    },
    "ch_123.jpg": {
        "mt": "Spring Festival holiday  \nGo back to work on the eighth day of the first lunar month",
        "ref": [
            "Spring Festival Holiday",
            "Available from 8th day"
        ],
        "src": [
            "春节放假",
            "初八上班"
        ]
    },
    "ch_59.jpg": {
        "mt": "Dangerous, No Passage Allowed",
        "ref": [
            "Danger No entry"
        ],
        "src": [
            "危险禁止通行"
        ]
    },
    "ch_88.jpg": {
        "mt": "Three Gorges Ship Lock",
        "ref": [
            "Three Gorges Ship Lock"
        ],
        "src": [
            "三峡船闸"
        ]
    },
    "ch_25.jpg": {
        "mt": "Get off the vehicle passage  \nPlease do not stand people",
        "ref": [
            "Exit lane",
            "No standing"
        ],
        "src": [
            "下车通道",
            "请勿站人"
        ]
    },
    "ch_2.jpg": {
        "mt": "Departures Hall",
        "ref": [
            "Departures Hall",
            "Departures Hall"
        ],
        "src": [
            "出发大厅",
            "Departures Hall"
        ]
    },
    "ch_151.jpg": {
        "mt": "Very dangerous  \nMay explode at any time!!",
        "ref": [
            "Danger",
            "Anytime, will explode"
        ],
        "src": [
            "好危",
            "随时会",
            "！爆炸！"
        ]
    },
    "ch_180.jpg": {
        "mt": "Heater is on sale",
        "ref": [
            "Warmer, off promotions"
        ],
        "src": [
            "取暖器",
            "降价了"
        ]
    },
    "ch_22.jpg": {
        "mt": "",
        "ref": [
            "Share healthy life"
        ],
        "src": [
            "共享健康生活"
        ]
    },
    "ch_5.jpg": {
        "mt": "CAR God State Car Rental",
        "ref": [
            "China Auto Rental",
            "CAR"
        ],
        "src": [
            "神州租车",
            "CAR"
        ]
    },
    "ch_156.jpg": {
        "mt": "Large Vehicle Parking Lot",
        "ref": [
            "Truck parking Area"
        ],
        "src": [
            "大车停车场"
        ]
    },
    "ch_187.jpg": {
        "mt": "Can \"eat\" toys",
        "ref": [
            "can, “eat”, toys"
        ],
        "src": [
            "可以",
            "“吃”",
            "的玩具"
        ]
    }
}