{
    "文字完全在商品主体上/文字完全在商品主体上_0004.jpg": {
        "mt": "ملمس ناعم ومنعش\nاستمتع بـ \"التنفس\"\nهيكل الشاش المتعدد الفراغات، يحقق تداول الهواء حول البشرة",
        "src": [
            "触感柔滑清爽",
            "享受“呼吸”",
            "多空纱布结构，实现肌肤周围的空气循坏"
        ]
    },
    "文字完全在商品主体上/文字完全在商品主体上_0034.jpg": {
        "mt": "مظهر نحيف للجزء العلوي  \nأجواء الخريف والشتاء",
        "src": [
            "上身显瘦",
            "秋冬氛围"
        ]
    },
    "文字完全在商品主体上/文字完全在商品主体上_0041.jpg": {
        "mt": "كمية الريش كافية للتدفئة\nارتديه للتزلج وستكون بخير!",
        "src": [
            "充绒量足 巨保暖",
            "滑雪穿他就可以！"
        ]
    },
    "文字完全在商品主体上/文字完全在商品主体上_0047.jpg": {
        "mt": "هو شعور بالخفقان\nأساسي ومتعدد الاستخدامات\nألوان الأرض",
        "src": [
            "是心动的感觉",
            "基础又百搭",
            "大地色系"
        ]
    },
    "文字完全在商品主体上/文字完全在商品主体上_0090.jpg": {
        "mt": "FqumaJeux pasobldansmae  \nJe uals quotu ne ylendras jaais amon tour.  \nJe pxonu toujours scul  \nSoo tujour belle, ma bolle  \n奶里奶气的软奶蓝棉服",
        "src": [
            "奶里奶气的软奶蓝棉服"
        ]
    }
}