{
    "同行文本高度不同/同行文本高度不同_0036.jpg": {
        "mt": "لانكوم\n\nالترميم المُحدّث مصدر الراحة وتخفيف الاحمرار\n\nلانكوم\n\nباريس\n\nتثبيط 5 عوامل احمرار رئيسية\n\nIL-1α | PGE2 | TNF-α | IL-6 | IL-8\n\nخفض درجة الحرارة بمقدار 6°C لإطفاء الحريق فورًا\n\n1 استخدام تقليل الاحمرار -22%\n\nTONIQUE CONFORT\n\nقبل الاستخدام | بعد التدليك | بعد الرطوبة\n\n1. البيانات البحثية للعلامة التجارية والمؤسسات التعاونية، نتائج اختبارات الجلد للمستخدمين بعد 30 ثانية من الاستخدام.\n2. البيانات البحثية للعلامة التجارية والمؤسسات التعاونية، نتائج تقييم الأداة لوجه المستخدم قبل وبعد الاستخدام، النتائج الفعلية تختلف من شخص لآخر.",
        "src": [
            "LANCOME",
            "修护升级 源头舒缓退红",
            "抑制5大泛红因子",
            "IL-1a|PGE2|TNF-a|IL-6|IL-8",
            "降温6℃即刻灭火¹",
            "1次使用 泛红-22%²",
            "使用前",
            "涂抹后",
            "湿敷后",
            "1.品牌和合作机构研究数据，受试者使用30s后的肌肤测试结果。",
            "2.品牌和合作机构研究数据，受试者使用与未使用半脸的仪器评估结果，实际效果因人而异。"
        ]
    },
    "同行文本高度不同/同行文本高度不同_0044.jpg": {
        "mt": "تحليل المنتج!\n\nهناك لا شك أن السعادة هي أكثر شيء ثمين في العالم، بدونها الحياة بلا معنى. إذا كنت تريد معرفة كيف تحصل على السعادة، عليك:\n\nمخرج الماء القابل للتفكيك\n\nرأس مضخة المياه\n\nمحور مضخة المياه\n\nصمام الثابتة\n\nشبكة مضخة المياه\n\nمدخل الماء القابل للتفكيك\n\nمصاصة مضخة المياه",
        "src": [
            "ANALYSIS",
            "产品解析！",
            "水泵机头",
            "可拆卸出水口",
            "水泵转芯",
            "固定阀",
            "可拆卸进水口",
            "水泵格栅",
            "水泵吸盘"
        ]
    },
    "同行文本高度不同/同行文本高度不同_0049.jpg": {
        "mt": "HYDROGEN WATER\nاجعل شرب الماء · يصبح تغذية\nأعطِني ثلاث دقائق لتغيير ماء كوبك ~\nالكهرباء الدقيقة كأس ماء غني بالهيدروجين\nسرعة التحليل الكهربائي | عمليات ذكية\nالماء المضاد للأكسدة | هدية ممتازة",
        "src": [
            "HYDROGEN WATER",
            "让喝水·变成养生",
            "给我三分钟 改变你杯中的水~",
            "微电解富氢水杯",
            "快速点解",
            "智能操作",
            "抗氧化水",
            "送礼佳品"
        ]
    },
    "同行文本高度不同/同行文本高度不同_0050.jpg": {
        "mt": "الركبة غير مريحة في الغالب هي بسبب التبريد\n\nمشكلات الركبة تصبح شائعة بين الشباب\n\n1. ألم الركبة\n2. مشاكل معقدة\n3. ألم بسبب الرياح والبرد\n\n3. التكييف لفترات طويلة\n4. مرض التكييف\n5. مرض الرطوبة",
        "src": [
            "膝关节不适大都是 受凉引起",
            "膝部问题低龄化",
            "1.膝部疼痛",
            "2.复杂麻烦",
            "3.风吹疼痛",
            "3.长期空调",
            "4.空调病",
            "3.风湿病"
        ]
    },
    "同行文本高度不同/同行文本高度不同_0052.jpg": {
        "mt": "مقارنة بين الإصدار الجديد والقديم\n\nGH بلاستيكية خالية من الروائح الكريهة\nزاوية ارتباط الأسنان\n\nالجلد اللين يحتوي على رائحة قليلاً\nزاوية تثبيت الوسادة\n\nيوجد أسنان\n\nلا يوجد أسنان",
        "src": [
            "改造新版与旧版对比",
            "GH塑质无异味",
            "软胶稍有异味",
            "卡齿咬合角度",
            "垫片加紧角度",
            "有卡齿",
            "没卡齿"
        ]
    },
    "同行文本高度不同/同行文本高度不同_0060.jpg": {
        "mt": "رقصة زهرة عباد الشمس (إصدار الشحن)\n\n200 أغنية\n\n1. أغنية عيد ميلاد سعيد وغريبة\n2. موسيقى إيقاع الطبول الأفريقية\n\nاشترِ واحصل على هدية\n\nكابل شحن USB\n\nوظائف متعددة\n\n1. تعلم الكلام والتقليد\n2. 200 أغنية\n3. رقص سحري\n4. شحن عبر USB\n5. يمكن التسجيل لمدة 15 ثانية\n6. يمكن الإضاءة",
        "src": [
            "舞蹈向日葵",
            "（充电款）",
            "200首歌曲",
            "1.生日快乐搞怪歌",
            "2.非洲鼓点音乐",
            "买就送",
            "usb充电线",
            "多种功能",
            "1.学说话复读",
            "2.200首歌曲",
            "3.魔性抖舞",
            "4.USB充电",
            "5.可录音15秒",
            "6.可发光"
        ]
    }
}