{
    "logo/logo_0005.jpg": {
        "mt": "Baseus\nThree-in-one design\nSolves cleaning challenges\nThoroughly removes dust and stains without residue\nPowerful small brush head\nCleans stubborn stains in crevices\nDense large brush head\nCleans dust on the surface of earphones\nMemory foam head\nDeep cleans earphone charging case",
        "src": [
            "Baseus倍思",
            "一笔三头",
            "解决清洁难题",
            "灰尘污渍 彻底清理不残留",
            "强力小刷头",
            "清理缝隙顽固污渍",
            "细密大刷头",
            "清理耳机表面灰尘",
            "记忆海绵头",
            "深入清洁耳机充电仓"
        ]
    },
    "logo/logo_0008.jpg": {
        "mt": "Sai Whale\nWatching dramas while lying down\nMore comfortable\nNewly upgraded crescent-shaped pillow stand\nU5P supports mobile phones\nU5\nU5T\nUniversal for mobile phones and tablets\nWin a dust cover\nGet it for free by shopping around",
        "src": [
            "赛鲸",
            "躺着追剧",
            "更舒适",
            "新升级月牙形抱枕支架",
            "支持手机",
            "U5",
            "手机平板通用",
            "赢防尘罩",
            "发逛逛即送"
        ]
    },
    "logo/logo_0033.jpg": {
        "mt": "MOCA ROSE  \nHigh-quality enameled cast iron pot series  \nMocha color  \n99.8% high purity | Even heat distribution | Non-stick  \n￥135  \nJoin to receive a large coupon package  \nMembers get free gifts for sharing orders  \nSauce dishes * 4  \n(For single payments between 500-1000 yuan)  \nSmall soup spoons * 6  \n(For single payments over 1000 yuan)  \nFinal price:  \n579  \nGo to the details page to claim coupons before ordering  \n￥  \nStarting from",
        "src": [
            "MOCA ROSE",
            "高质珐琅精铁锅系列",
            "摩卡色",
            "99.8%高纯度 | 导热均匀 | 不易粘锅",
            "¥135券",
            "入会领取大额券包",
            "会员晒单送",
            "蘸料碟*4",
            "（单笔实付500-1000元享）",
            "小汤勺*6",
            "（单笔实付1000元以上享）",
            "到手价：",
            "579",
            "去详情页先领券再下单",
            "¥",
            "起"
        ]
    },
    "logo/logo_0058.jpg": {
        "mt": "Benks\nProtect What You Love\nBottBatter\nOriginal Screen Project\nA Visual Feast on the Screen\nExclusive High Coverage\nFirst Launch with Corning Material and Hot Bending Process, Unobstructed Screen Fit\nAn Experience\nA Life\nA Pursuit",
        "src": [
            "Benks邦克仕",
            "护你所爱",
            "pretect batter",
            "原屏计划",
            "荧幕视觉般的享受",
            "高占比覆盖独享",
            "首发康宁材质热弯工艺，屏幕适配无遮挡",
            "An experience",
            "An life",
            "An pursuit"
        ]
    },
    "logo/logo_0064.jpg": {
        "mt": "Caitang TIMAGE\nBlending and Coloring\nEffortless and Skillful\nComplete Set Selection\nEach One Stands Out\nCustom Brush Shapes\nDedicated Application for Each Area\nPremium Hair Selection\nStrong Powder Pickup and Even Release\nCaitang\nTIMAGE",
        "src": [
            "彩棠TIMAGE",
            "晕染绘色",
            "得心应手",
            "成套优选",
            "每一支都独当一面",
            "定制刷型",
            "分区上妆各司其职",
            "臻选毛丝",
            "抓粉有力释粉均匀"
        ]
    },
    "logo/logo_0099.jpg": {
        "mt": "South Africa\nWholesale Store\nLiquid\nPcant Pro\nPcant\nPuantPro Botanical Research Plus\nPuantPro Botanical Research Plus\nNext Day Delivery\nGenuine Guaranteed\nSupports Drop Shipping\nSome regions",
        "src": [
            "南菲批发店",
            "次日达",
            "保证正品",
            "支持代发",
            "部分地区"
        ]
    }
}