{
    "倾斜文本/倾斜文本_0001.jpg": {
        "mt": "Weicher Absatz, nicht reibend\n\nWeicher Absatz, nicht reibend, pflegt die Füße des Babys",
        "src": [
            "柔软后跟",
            "柔软后跟不易磨脚",
            "柔软后跟，不易磨脚，呵护宝宝脚踝"
        ]
    },
    "倾斜文本/倾斜文本_0012.jpg": {
        "mt": "Tiefe Grau  \nDoppel-Sitzer, extra groß  \n\nSeitenbreite 80cm  \nSitztiefe 45cm  \nGesamthöhe 68cm  \nSitzhöhe 30cm  \nSitzlänge 95cm  \n\nMöbel- und Heimtextil PLUS-Mitgliedstag  \nQuellfabrik Schäden kostenlos nachsenden Ein Stück neunzig Prozent Rabatt",
        "src": [
            "深灰色",
            "双人位 特大款",
            "侧宽80cm",
            "整高68cm",
            "座深45cm",
            "座高30",
            "座长95cm",
            "家具家装PLUS会员日",
            "源头工厂",
            "破损免费补发",
            "发一件九折",
            "PLUS"
        ]
    },
    "倾斜文本/倾斜文本_0014.jpg": {
        "mt": "Kleine Größe, bequem und nimmt nicht viel Platz ein  \nKompakte Größe, passt in jede Umgebung, kann leicht platziert werden. Sofa und Bett in einem  \n\nBeschäftigt nur  \n≈1m² für Wohnzimmer | für Balkon  \n\nGesamtbreite: 104cm  \nGesamt Tiefe: 100cm",
        "src": [
            "小身姿舒适 不占空间",
            "小巧身姿，不挑场景可轻松放置 沙发和床一键拥有",
            "占地仅≈1m²",
            "放客厅|放阳台",
            "总深：100cm"
        ]
    },
    "倾斜文本/倾斜文本_0026.jpg": {
        "mt": "Komfortabel und atmungsaktiv\n\nLeichtgewichtigkeit ▼ Leichtfunktionalität\nDünne Nylon-Materialien, die auf dem Körper leicht und üppig wirken. Die Stoffoberfläche wird durch eine Faltenverarbeitung behandelt, mit einem mattierten Finish und natürlichen Mustern.",
        "src": [
            "舒适透气",
            "轻量感 轻机能 ",
            "轻薄尼龙面料，上身体感轻盈，布面洗皱工艺处理，哑光质感，自带纹理"
        ]
    },
    "倾斜文本/倾斜文本_0029.jpg": {
        "mt": "// Getränkebeschichtete Rohstoffe\n\nReibungsarm, abgerundete Ecken ohne Spuren und keine Beulen\n\nVerstärkt und verdickt, aktualisierte Version",
        "src": [
            "拿货节",
            "浸胶原材",
            "防滑 圆角无痕不鼓包",
            "加粗加厚升级款"
        ]
    }
}